sloth_ci/ext/openvz_exec.py
sloth_ci.ext.openvz_exec-1.0.5.dist-info/DESCRIPTION.rst
sloth_ci.ext.openvz_exec-1.0.5.dist-info/METADATA
sloth_ci.ext.openvz_exec-1.0.5.dist-info/RECORD
sloth_ci.ext.openvz_exec-1.0.5.dist-info/WHEEL
sloth_ci.ext.openvz_exec-1.0.5.dist-info/metadata.json
sloth_ci.ext.openvz_exec-1.0.5.dist-info/top_level.txt
